chic/__init__.py
chic/atomic_cluster.py
chic/bonds.py
chic/cif.py
chic/decorate.py
chic/gulp.py
chic/lammps.py
chic/net.py
chic/rattle.py
chic/scatty.py
chic/sort_sites.py
chic/structure.py
chic/templates.py
chic/tidy.py
chic/utils.py
chic/vasp.py
chic/vector.py
chic/xyz.py
chic/zif.py
chic/coarse_graining_methods/__init__.py
chic/coarse_graining_methods/defaults.py
chic_lib-0.1.19.dist-info/LICENSE
chic_lib-0.1.19.dist-info/METADATA
chic_lib-0.1.19.dist-info/WHEEL
chic_lib-0.1.19.dist-info/top_level.txt
chic_lib-0.1.19.dist-info/RECORD
