Metadata-Version: 2.1
Name: chic-lib
Version: 0.1.19
Summary: Coarse-grainig hybrid and inorganic crystals (CHIC)
Home-page: https://github.com/tcnicholas/chic
Author: Thomas C Nicholas
Author-email: Thomas C Nicholas <tcnicholas@me.com>
License: GNU GENERAL PUBLIC LICENSE
Project-URL: Homepage, https://github.com/tcnicholas/chic
Keywords: chemistry,machine learning,coarse-graining
Classifier: License :: OSI Approved :: MIT License
Classifier: Programming Language :: Python
Classifier: Programming Language :: Python :: 3
Requires-Python: >=3.8
License-File: LICENSE
Requires-Dist: numpy
Requires-Dist: scipy
Requires-Dist: scikit-learn
Requires-Dist: pymatgen
Requires-Dist: ase
Requires-Dist: networkx
Requires-Dist: ipython
Provides-Extra: dev
Requires-Dist: notebook; extra == "dev"
Requires-Dist: pytest==7.2.0; extra == "dev"
Requires-Dist: sphinx; extra == "dev"
Requires-Dist: furo; extra == "dev"
Requires-Dist: nbsphinx; extra == "dev"
Requires-Dist: sphinx-autobuild; extra == "dev"
Requires-Dist: pytest-cov; extra == "dev"
Requires-Dist: build; extra == "dev"
Requires-Dist: bumpver; extra == "dev"
Requires-Dist: twine; extra == "dev"
Requires-Dist: ruff; extra == "dev"
Requires-Dist: sphinx-autodoc-typehints; extra == "dev"
Requires-Dist: sphinx-design; extra == "dev"
Requires-Dist: sphinx-copybutton; extra == "dev"
Requires-Dist: sphinx-codeautolink; extra == "dev"
Requires-Dist: sphinxext-opengraph; extra == "dev"
